{
  "fields": [
    {
      "name": "_id",
      "path": "_id",
      "count": 100,
      "types": [
        {
          "name": "ObjectID",
          "bsonType": "ObjectID",
          "path": "_id",
          "count": 100,
          "values": [
            "60e32d7da7329589de0b0c4a",
            "60e32d7da7329589de0b0c52",
            "60e32d7da7329589de0b0c75",
            "60e32d7da7329589de0b0c5c",
            "60e32d7da7329589de0b0c77",
            "60e32d7da7329589de0b0c24",
            "60e32d7da7329589de0b0c66",
            "60e32d7da7329589de0b0c38",
            "60e32d7da7329589de0b0c2d",
            "60e32d7da7329589de0b0c36",
            "60e32d7da7329589de0b0c70",
            "60e32d7da7329589de0b0c62",
            "60e32d7da7329589de0b0c48",
            "60e32d7da7329589de0b0c45",
            "60e32d7da7329589de0b0c4c",
            "60e32d7da7329589de0b0c3f",
            "60e32d7da7329589de0b0c65",
            "60e32d7da7329589de0b0c56",
            "60e32d7da7329589de0b0c25",
            "60e32d7da7329589de0b0c6a",
            "60e32d7da7329589de0b0c53",
            "60e32d7da7329589de0b0c2b",
            "60e32d7da7329589de0b0c33",
            "60e32d7da7329589de0b0c28",
            "60e32d7da7329589de0b0c71",
            "60e32d7da7329589de0b0c81",
            "60e32d7da7329589de0b0c37",
            "60e32d7da7329589de0b0c5a",
            "60e32d7da7329589de0b0c6b",
            "60e32d7da7329589de0b0c2f",
            "60e32d7da7329589de0b0c47",
            "60e32d7da7329589de0b0c3b",
            "60e32d7da7329589de0b0c44",
            "60e32d7da7329589de0b0c3a",
            "60e32d7da7329589de0b0c64",
            "60e32d7da7329589de0b0c78",
            "60e32d7da7329589de0b0c68",
            "60e32d7da7329589de0b0c7b",
            "60e32d7da7329589de0b0c84",
            "60e32d7da7329589de0b0c5d",
            "60e32d7da7329589de0b0c5f",
            "60e32d7da7329589de0b0c2e",
            "60e32d7da7329589de0b0c5b",
            "60e32d7da7329589de0b0c4b",
            "60e32d7da7329589de0b0c6e",
            "60e32d7da7329589de0b0c86",
            "60e32d7da7329589de0b0c3d",
            "60e32d7da7329589de0b0c41",
            "60e32d7da7329589de0b0c4d",
            "60e32d7da7329589de0b0c4e",
            "60e32d7da7329589de0b0c35",
            "60e32d7da7329589de0b0c3e",
            "60e32d7da7329589de0b0c2c",
            "60e32d7da7329589de0b0c69",
            "60e32d7da7329589de0b0c87",
            "60e32d7da7329589de0b0c7d",
            "60e32d7da7329589de0b0c39",
            "60e32d7da7329589de0b0c50",
            "60e32d7da7329589de0b0c46",
            "60e32d7da7329589de0b0c61",
            "60e32d7da7329589de0b0c26",
            "60e32d7da7329589de0b0c58",
            "60e32d7da7329589de0b0c49",
            "60e32d7da7329589de0b0c51",
            "60e32d7da7329589de0b0c6f",
            "60e32d7da7329589de0b0c76",
            "60e32d7da7329589de0b0c59",
            "60e32d7da7329589de0b0c85",
            "60e32d7da7329589de0b0c73",
            "60e32d7da7329589de0b0c40",
            "60e32d7da7329589de0b0c74",
            "60e32d7da7329589de0b0c80",
            "60e32d7da7329589de0b0c31",
            "60e32d7da7329589de0b0c42",
            "60e32d7da7329589de0b0c57",
            "60e32d7da7329589de0b0c43",
            "60e32d7da7329589de0b0c83",
            "60e32d7da7329589de0b0c7e",
            "60e32d7da7329589de0b0c6c",
            "60e32d7da7329589de0b0c5e",
            "60e32d7da7329589de0b0c34",
            "60e32d7da7329589de0b0c79",
            "60e32d7da7329589de0b0c60",
            "60e32d7da7329589de0b0c2a",
            "60e32d7da7329589de0b0c30",
            "60e32d7da7329589de0b0c54",
            "60e32d7da7329589de0b0c6d",
            "60e32d7da7329589de0b0c7c",
            "60e32d7da7329589de0b0c7f",
            "60e32d7da7329589de0b0c63",
            "60e32d7da7329589de0b0c7a",
            "60e32d7da7329589de0b0c55",
            "60e32d7da7329589de0b0c82",
            "60e32d7da7329589de0b0c32",
            "60e32d7da7329589de0b0c67",
            "60e32d7da7329589de0b0c72",
            "60e32d7da7329589de0b0c3c",
            "60e32d7da7329589de0b0c29",
            "60e32d7da7329589de0b0c27",
            "60e32d7da7329589de0b0c4f"
          ],
          "total_count": 0,
          "probability": 1,
          "unique": 100,
          "has_duplicates": false
        }
      ],
      "total_count": 100,
      "type": "ObjectID",
      "has_duplicates": false,
      "probability": 1
    },
    {
      "name": "1-open",
      "path": "1-open",
      "count": 100,
      "types": [
        {
          "name": "String",
          "bsonType": "String",
          "path": "1-open",
          "count": 100,
          "values": [
            "159.7500",
            "150.6800",
            "148.5800",
            "145.8100",
            "144.6600",
            "167.7000",
            "142.9000",
            "165.0000",
            "160.0800",
            "164.8599",
            "147.2500",
            "145.9800",
            "154.7200",
            "157.0500",
            "156.8600",
            "159.0700",
            "142.9800",
            "147.5700",
            "165.6500",
            "137.9700",
            "150.7000",
            "165.0300",
            "163.0000",
            "168.6200",
            "148.0400",
            "129.4900",
            "165.6300",
            "149.7100",
            "138.9400",
            "165.9700",
            "152.4100",
            "162.5100",
            "157.3600",
            "164.6100",
            "142.3400",
            "142.1500",
            "143.7400",
            "138.1800",
            "128.9100",
            "146.5500",
            "148.2100",
            "158.7000",
            "147.5100",
            "155.6100",
            "145.4900",
            "127.4500",
            "159.9800",
            "156.7000",
            "154.8700",
            "154.4800",
            "165.2700",
            "158.1600",
            "163.4200",
            "137.9500",
            "127.6300",
            "140.6200",
            "163.6800",
            "153.6000",
            "155.3900",
            "147.4200",
            "163.7000",
            "147.2100",
            "156.4600",
            "153.8500",
            "144.7600",
            "147.2800",
            "149.1900",
            "128.1900",
            "146.0000",
            "157.7000",
            "145.7000",
            "131.5100",
            "163.9300",
            "155.4700",
            "144.0000",
            "152.0700",
            "130.0800",
            "137.2000",
            "139.4900",
            "147.2600",
            "165.1800",
            "140.0000",
            "146.8000",
            "167.0550",
            "165.7800",
            "146.8000",
            "141.9000",
            "137.1000",
            "136.4700",
            "146.9100",
            "138.2400",
            "141.5400",
            "127.4900",
            "164.3000",
            "141.9800",
            "149.1000",
            "160.2600",
            "168.4500",
            "165.5700",
            "154.5900"
          ],
          "total_count": 0,
          "probability": 1,
          "unique": 99,
          "has_duplicates": true
        }
      ],
      "total_count": 100,
      "type": "String",
      "has_duplicates": true,
      "probability": 1
    },
    {
      "name": "2-high",
      "path": "2-high",
      "count": 100,
      "types": [
        {
          "name": "String",
          "bsonType": "String",
          "path": "2-high",
          "count": 100,
          "values": [
            "160.6900",
            "153.4550",
            "149.0800",
            "148.7500",
            "147.9600",
            "168.9800",
            "144.4800",
            "165.7300",
            "165.2100",
            "167.1400",
            "147.2650",
            "146.5300",
            "155.9000",
            "157.3751",
            "157.5050",
            "160.0800",
            "143.2600",
            "148.9200",
            "167.3700",
            "140.0400",
            "150.8800",
            "166.8600",
            "164.5400",
            "168.8450",
            "148.9200",
            "133.3600",
            "166.6500",
            "150.4500",
            "139.5000",
            "165.9971",
            "154.8100",
            "164.1100",
            "158.3000",
            "165.6900",
            "144.6300",
            "144.1100",
            "143.9800",
            "139.7700",
            "130.9100",
            "146.6050",
            "148.4400",
            "159.6700",
            "148.5900",
            "159.2600",
            "145.5000",
            "129.1200",
            "160.2900",
            "158.8100",
            "156.7300",
            "155.7400",
            "166.1400",
            "159.3800",
            "165.2400",
            "142.5300",
            "128.7000",
            "140.6400",
            "165.4200",
            "154.0400",
            "157.9350",
            "148.3600",
            "166.1600",
            "147.5000",
            "157.7900",
            "155.0800",
            "144.8200",
            "151.4600",
            "149.5050",
            "130.4600",
            "147.8200",
            "158.9050",
            "148.2900",
            "136.4700",
            "166.9000",
            "156.2510",
            "147.3800",
            "154.7750",
            "131.1600",
            "140.9500",
            "140.9900",
            "147.7700",
            "165.2100",
            "144.2500",
            "147.1600",
            "168.5800",
            "166.6500",
            "151.1200",
            "141.9400",
            "138.2500",
            "138.3100",
            "147.4800",
            "140.1900",
            "144.9800",
            "128.8300",
            "164.8800",
            "143.0700",
            "150.6400",
            "160.6350",
            "170.4100",
            "166.3200",
            "156.0500"
          ],
          "total_count": 0,
          "probability": 1,
          "unique": 97,
          "has_duplicates": true
        }
      ],
      "total_count": 100,
      "type": "String",
      "has_duplicates": true,
      "probability": 1
    },
    {
      "name": "3-low",
      "path": "3-low",
      "count": 100,
      "types": [
        {
          "name": "String",
          "bsonType": "String",
          "path": "3-low",
          "count": 100,
          "values": [
            "158.5000",
            "149.4400",
            "144.1100",
            "145.7000",
            "142.0800",
            "167.0100",
            "142.6100",
            "163.3200",
            "159.1300",
            "163.6300",
            "142.8200",
            "144.3800",
            "152.0700",
            "155.8800",
            "154.0200",
            "157.7400",
            "141.3500",
            "145.8700",
            "164.6900",
            "137.6142",
            "148.8500",
            "164.7900",
            "162.5100",
            "163.2000",
            "146.0300",
            "129.4900",
            "165.3700",
            "148.6900",
            "135.1250",
            "160.5300",
            "151.8100",
            "161.5500",
            "154.8600",
            "163.3200",
            "142.2050",
            "139.9500",
            "141.0506",
            "138.1200",
            "128.2500",
            "143.8400",
            "146.6900",
            "157.2500",
            "145.5000",
            "155.3400",
            "142.0700",
            "126.9800",
            "158.8500",
            "156.3459",
            "154.8300",
            "152.8401",
            "163.8000",
            "157.3700",
            "162.4600",
            "136.7600",
            "126.8400",
            "136.3700",
            "162.8200",
            "152.4800",
            "154.5300",
            "145.7200",
            "163.7000",
            "144.5100",
            "153.6500",
            "152.0900",
            "141.9000",
            "146.7200",
            "147.8000",
            "128.0000",
            "145.1300",
            "156.9500",
            "145.4401",
            "131.3700",
            "163.8000",
            "153.9300",
            "143.0200",
            "151.7200",
            "128.4400",
            "136.8100",
            "138.8100",
            "146.4100",
            "162.1200",
            "140.0000",
            "144.6800",
            "166.4100",
            "164.2700",
            "145.5600",
            "139.7358",
            "133.7900",
            "134.2800",
            "145.6100",
            "138.0800",
            "140.6800",
            "126.0750",
            "163.1100",
            "140.3100",
            "148.0200",
            "158.8600",
            "168.4500",
            "163.2300",
            "154.0100"
          ],
          "total_count": 0,
          "probability": 1,
          "unique": 98,
          "has_duplicates": true
        }
      ],
      "total_count": 100,
      "type": "String",
      "has_duplicates": true,
      "probability": 1
    },
    {
      "name": "4-close",
      "path": "4-close",
      "count": 100,
      "types": [
        {
          "name": "String",
          "bsonType": "String",
          "path": "4-close",
          "count": 100,
          "values": [
            "158.6800",
            "152.5400",
            "145.1000",
            "147.4200",
            "147.3300",
            "168.5000",
            "143.4900",
            "165.0000",
            "164.9000",
            "166.5100",
            "143.3000",
            "146.1500",
            "152.3000",
            "156.8600",
            "156.8800",
            "158.0100",
            "141.4400",
            "147.1600",
            "166.9400",
            "138.4200",
            "150.3600",
            "166.0200",
            "164.5100",
            "164.7800",
            "146.9900",
            "131.7100",
            "165.9200",
            "149.9900",
            "136.0800",
            "162.1300",
            "154.0800",
            "163.7600",
            "154.9900",
            "164.1200",
            "144.5700",
            "142.6800",
            "143.7300",
            "138.7100",
            "130.6800",
            "145.9900",
            "147.7800",
            "158.1700",
            "148.5300",
            "158.9800",
            "142.5800",
            "128.3100",
            "159.7400",
            "156.8700",
            "156.3900",
            "154.5300",
            "164.0900",
            "158.5800",
            "164.5000",
            "142.2800",
            "128.2300",
            "137.0800",
            "164.5200",
            "153.3500",
            "157.1500",
            "147.1300",
            "165.2300",
            "145.1000",
            "154.4300",
            "154.6300",
            "144.6800",
            "150.2700",
            "148.5400",
            "129.6200",
            "147.7500",
            "158.6400",
            "146.7500",
            "135.9500",
            "166.2700",
            "155.5300",
            "147.1800",
            "154.7300",
            "128.5600",
            "139.8900",
            "139.9500",
            "147.5700",
            "162.2300",
            "142.5900",
            "147.0400",
            "168.2100",
            "164.6800",
            "150.3400",
            "140.7100",
            "135.2600",
            "136.9400",
            "146.0600",
            "139.2500",
            "144.3300",
            "128.4900",
            "163.8100",
            "142.3700",
            "148.5400",
            "160.1300",
            "169.4500",
            "164.2500",
            "154.8000"
          ],
          "total_count": 0,
          "probability": 1,
          "unique": 98,
          "has_duplicates": true
        }
      ],
      "total_count": 100,
      "type": "String",
      "has_duplicates": true,
      "probability": 1
    },
    {
      "name": "5-volume",
      "path": "5-volume",
      "count": 100,
      "types": [
        {
          "name": "String",
          "bsonType": "String",
          "path": "5-volume",
          "count": 100,
          "values": [
            "2987640",
            "2584455",
            "5806098",
            "2141855",
            "5048348",
            "2029377",
            "2034531",
            "3239263",
            "3681406",
            "2486506",
            "4031004",
            "2851170",
            "3487353",
            "1541489",
            "2798825",
            "2484248",
            "2957303",
            "3247306",
            "2685879",
            "2638925",
            "2692069",
            "2327649",
            "1630124",
            "3433417",
            "2587554",
            "3419709",
            "2516443",
            "3479952",
            "4905394",
            "4194569",
            "2269772",
            "3827978",
            "2417796",
            "3384656",
            "2629367",
            "4461743",
            "2687546",
            "2972111",
            "2730821",
            "2132419",
            "1783371",
            "6900458",
            "2901231",
            "2617982",
            "3173793",
            "3732993",
            "2828368",
            "3424122",
            "2194909",
            "3025258",
            "2700099",
            "3731658",
            "2697851",
            "2766588",
            "2749151",
            "3489675",
            "2454835",
            "2712846",
            "1892786",
            "2399603",
            "2331836",
            "2526892",
            "3900087",
            "2636183",
            "3278463",
            "4283406",
            "2259141",
            "2873279",
            "3147700",
            "1956937",
            "3049798",
            "3688430",
            "3726439",
            "3031135",
            "2161652",
            "3527061",
            "3088737",
            "4099537",
            "2274119",
            "1869013",
            "3024778",
            "4393693",
            "2295770",
            "2417124",
            "3140738",
            "4821052",
            "5098313",
            "3472320",
            "4814427",
            "2960081",
            "2929140",
            "6400505",
            "2269742",
            "2125719",
            "2220576",
            "2420091",
            "2437025",
            "9185989",
            "2785869",
            "2726404"
          ],
          "total_count": 0,
          "probability": 1,
          "unique": 100,
          "has_duplicates": false
        }
      ],
      "total_count": 100,
      "type": "String",
      "has_duplicates": false,
      "probability": 1
    },
    {
      "name": "index",
      "path": "index",
      "count": 100,
      "types": [
        {
          "name": "String",
          "bsonType": "String",
          "path": "index",
          "count": 100,
          "values": [
            "2021-05-10",
            "2021-04-28",
            "2021-03-09",
            "2021-04-14",
            "2021-03-05",
            "2021-07-02",
            "2021-03-30",
            "2021-06-04",
            "2021-06-21",
            "2021-06-08",
            "2021-03-16",
            "2021-04-06",
            "2021-05-12",
            "2021-05-17",
            "2021-05-06",
            "2021-05-25",
            "2021-03-31",
            "2021-04-22",
            "2021-07-01",
            "2021-03-24",
            "2021-04-27",
            "2021-06-23",
            "2021-06-11",
            "2021-06-28",
            "2021-03-15",
            "2021-02-19",
            "2021-06-07",
            "2021-04-16",
            "2021-03-23",
            "2021-06-17",
            "2021-05-13",
            "2021-06-01",
            "2021-05-18",
            "2021-06-02",
            "2021-04-01",
            "2021-03-04",
            "2021-03-26",
            "2021-03-01",
            "2021-02-16",
            "2021-04-13",
            "2021-04-09",
            "2021-06-18",
            "2021-04-15",
            "2021-05-07",
            "2021-03-18",
            "2021-02-11",
            "2021-05-27",
            "2021-05-21",
            "2021-05-05",
            "2021-05-04",
            "2021-06-09",
            "2021-05-26",
            "2021-06-22",
            "2021-03-25",
            "2021-02-10",
            "2021-02-25",
            "2021-06-03",
            "2021-04-30",
            "2021-05-14",
            "2021-04-07",
            "2021-06-30",
            "2021-04-20",
            "2021-05-11",
            "2021-04-29",
            "2021-03-17",
            "2021-03-08",
            "2021-04-19",
            "2021-02-12",
            "2021-03-11",
            "2021-05-24",
            "2021-03-10",
            "2021-02-22",
            "2021-06-15",
            "2021-05-20",
            "2021-04-21",
            "2021-05-19",
            "2021-02-17",
            "2021-02-24",
            "2021-03-22",
            "2021-04-12",
            "2021-06-10",
            "2021-03-03",
            "2021-04-08",
            "2021-06-24",
            "2021-06-16",
            "2021-04-26",
            "2021-03-19",
            "2021-02-26",
            "2021-02-23",
            "2021-04-05",
            "2021-03-02",
            "2021-04-23",
            "2021-02-18",
            "2021-06-14",
            "2021-03-29",
            "2021-03-12",
            "2021-05-28",
            "2021-06-25",
            "2021-06-29",
            "2021-05-03"
          ],
          "total_count": 0,
          "probability": 1,
          "unique": 100,
          "has_duplicates": false
        }
      ],
      "total_count": 100,
      "type": "String",
      "has_duplicates": false,
      "probability": 1
    }
  ],
  "count": 100
}