{
  "fields": [
    {
      "name": "_id",
      "path": "_id",
      "count": 100,
      "types": [
        {
          "name": "ObjectID",
          "bsonType": "ObjectID",
          "path": "_id",
          "count": 100,
          "values": [
            "60e32d04a7329589de0b098e",
            "60e32d04a7329589de0b0980",
            "60e32d04a7329589de0b0993",
            "60e32d04a7329589de0b0989",
            "60e32d04a7329589de0b09ad",
            "60e32d04a7329589de0b09c6",
            "60e32d04a7329589de0b0981",
            "60e32d04a7329589de0b0999",
            "60e32d04a7329589de0b0972",
            "60e32d04a7329589de0b09b7",
            "60e32d04a7329589de0b09ac",
            "60e32d04a7329589de0b0979",
            "60e32d04a7329589de0b0982",
            "60e32d04a7329589de0b09b1",
            "60e32d04a7329589de0b0995",
            "60e32d04a7329589de0b099b",
            "60e32d04a7329589de0b09c0",
            "60e32d04a7329589de0b09a1",
            "60e32d04a7329589de0b097d",
            "60e32d04a7329589de0b0984",
            "60e32d04a7329589de0b09c3",
            "60e32d04a7329589de0b0978",
            "60e32d04a7329589de0b09be",
            "60e32d04a7329589de0b097a",
            "60e32d04a7329589de0b0996",
            "60e32d04a7329589de0b0975",
            "60e32d04a7329589de0b098d",
            "60e32d04a7329589de0b09bc",
            "60e32d04a7329589de0b0986",
            "60e32d04a7329589de0b09bf",
            "60e32d04a7329589de0b096b",
            "60e32d04a7329589de0b097e",
            "60e32d04a7329589de0b099d",
            "60e32d04a7329589de0b09ca",
            "60e32d04a7329589de0b09b6",
            "60e32d04a7329589de0b09a3",
            "60e32d04a7329589de0b09a5",
            "60e32d04a7329589de0b09cb",
            "60e32d04a7329589de0b09b4",
            "60e32d04a7329589de0b09a6",
            "60e32d04a7329589de0b098f",
            "60e32d04a7329589de0b099e",
            "60e32d04a7329589de0b0998",
            "60e32d04a7329589de0b0977",
            "60e32d04a7329589de0b0987",
            "60e32d04a7329589de0b09b0",
            "60e32d04a7329589de0b096d",
            "60e32d04a7329589de0b0985",
            "60e32d04a7329589de0b09ae",
            "60e32d04a7329589de0b09c9",
            "60e32d04a7329589de0b097c",
            "60e32d04a7329589de0b099f",
            "60e32d04a7329589de0b09a7",
            "60e32d04a7329589de0b09a9",
            "60e32d04a7329589de0b096c",
            "60e32d04a7329589de0b0969",
            "60e32d04a7329589de0b0997",
            "60e32d04a7329589de0b097f",
            "60e32d04a7329589de0b09c1",
            "60e32d04a7329589de0b09c2",
            "60e32d04a7329589de0b0990",
            "60e32d04a7329589de0b0991",
            "60e32d04a7329589de0b09a4",
            "60e32d04a7329589de0b0988",
            "60e32d04a7329589de0b09b5",
            "60e32d04a7329589de0b099c",
            "60e32d04a7329589de0b09ba",
            "60e32d04a7329589de0b09bd",
            "60e32d04a7329589de0b098b",
            "60e32d04a7329589de0b099a",
            "60e32d04a7329589de0b096a",
            "60e32d04a7329589de0b09c4",
            "60e32d04a7329589de0b09b3",
            "60e32d04a7329589de0b098a",
            "60e32d04a7329589de0b09a8",
            "60e32d04a7329589de0b09a0",
            "60e32d04a7329589de0b0992",
            "60e32d04a7329589de0b09b9",
            "60e32d04a7329589de0b0974",
            "60e32d04a7329589de0b09b2",
            "60e32d04a7329589de0b0973",
            "60e32d04a7329589de0b0968",
            "60e32d04a7329589de0b09b8",
            "60e32d04a7329589de0b0983",
            "60e32d04a7329589de0b0970",
            "60e32d04a7329589de0b09af",
            "60e32d04a7329589de0b09bb",
            "60e32d04a7329589de0b09c5",
            "60e32d04a7329589de0b096f",
            "60e32d04a7329589de0b098c",
            "60e32d04a7329589de0b09c8",
            "60e32d04a7329589de0b097b",
            "60e32d04a7329589de0b09a2",
            "60e32d04a7329589de0b0976",
            "60e32d04a7329589de0b096e",
            "60e32d04a7329589de0b09ab",
            "60e32d04a7329589de0b0971",
            "60e32d04a7329589de0b09c7",
            "60e32d04a7329589de0b09aa",
            "60e32d04a7329589de0b0994"
          ],
          "total_count": 0,
          "probability": 1,
          "unique": 100,
          "has_duplicates": false
        }
      ],
      "total_count": 100,
      "type": "ObjectID",
      "has_duplicates": false,
      "probability": 1
    },
    {
      "name": "1-open",
      "path": "1-open",
      "count": 100,
      "types": [
        {
          "name": "String",
          "bsonType": "String",
          "path": "1-open",
          "count": 100,
          "values": [
            "42.5000",
            "42.6600",
            "40.8700",
            "42.2400",
            "36.8700",
            "34.0600",
            "42.4800",
            "38.3200",
            "39.0100",
            "37.2700",
            "38.3500",
            "42.4700",
            "42.0200",
            "38.2900",
            "40.5500",
            "37.7500",
            "35.7300",
            "39.8100",
            "42.7700",
            "42.5800",
            "35.4200",
            "42.7600",
            "35.6500",
            "42.8600",
            "39.9300",
            "41.2800",
            "41.5500",
            "36.1400",
            "41.9000",
            "35.5200",
            "41.6300",
            "43.1000",
            "39.3900",
            "32.9700",
            "37.9200",
            "39.9100",
            "39.7700",
            "33.1200",
            "37.4200",
            "39.5300",
            "41.1300",
            "39.3100",
            "39.3500",
            "41.8100",
            "41.6500",
            "38.0800",
            "41.2700",
            "42.0200",
            "37.2100",
            "33.0000",
            "43.2400",
            "39.7300",
            "40.0000",
            "38.6200",
            "41.4600",
            "41.5600",
            "39.6700",
            "42.9500",
            "36.9600",
            "35.7400",
            "41.4800",
            "41.2000",
            "39.8000",
            "42.7000",
            "38.0300",
            "39.0000",
            "37.3800",
            "35.9700",
            "40.8600",
            "38.7500",
            "40.7600",
            "34.4500",
            "38.0000",
            "42.0600",
            "38.8300",
            "38.9800",
            "40.2400",
            "36.5500",
            "41.2800",
            "38.5100",
            "42.0200",
            "41.3700",
            "36.5400",
            "42.6900",
            "39.8800",
            "37.3600",
            "37.0300",
            "34.2000",
            "40.1600",
            "42.3800",
            "33.9800",
            "43.2700",
            "39.9900",
            "41.8500",
            "40.4400",
            "38.0500",
            "39.1200",
            "34.0400",
            "38.6300",
            "40.8400"
          ],
          "total_count": 0,
          "probability": 1,
          "unique": 97,
          "has_duplicates": true
        }
      ],
      "total_count": 100,
      "type": "String",
      "has_duplicates": true,
      "probability": 1
    },
    {
      "name": "2-high",
      "path": "2-high",
      "count": 100,
      "types": [
        {
          "name": "String",
          "bsonType": "String",
          "path": "2-high",
          "count": 100,
          "values": [
            "42.9400",
            "42.7050",
            "41.0500",
            "42.8500",
            "37.7500",
            "34.6500",
            "42.8450",
            "39.3400",
            "39.3000",
            "37.7900",
            "38.7600",
            "42.7300",
            "42.2500",
            "38.9200",
            "41.1300",
            "38.7800",
            "36.0350",
            "39.8200",
            "43.4900",
            "42.7800",
            "35.8900",
            "42.9599",
            "35.9400",
            "43.2400",
            "40.2200",
            "41.5600",
            "42.3400",
            "36.8700",
            "42.1250",
            "36.0500",
            "41.9500",
            "43.1700",
            "39.4300",
            "33.3100",
            "38.1766",
            "40.1800",
            "40.1450",
            "33.4200",
            "37.7200",
            "40.1500",
            "42.2500",
            "39.4200",
            "39.8450",
            "41.8900",
            "42.0000",
            "38.3800",
            "41.8300",
            "42.6000",
            "37.7900",
            "33.4500",
            "43.3900",
            "39.8350",
            "40.2800",
            "38.9900",
            "41.5800",
            "41.7002",
            "39.9200",
            "43.2800",
            "37.0300",
            "36.5200",
            "42.0600",
            "41.5600",
            "39.8500",
            "42.9500",
            "38.0700",
            "39.0000",
            "37.7300",
            "36.9700",
            "42.0900",
            "38.7700",
            "41.3550",
            "35.2500",
            "38.3600",
            "42.4790",
            "39.5200",
            "40.3300",
            "41.0800",
            "37.1600",
            "41.9850",
            "39.9678",
            "42.1000",
            "41.4700",
            "37.5300",
            "43.2550",
            "40.2600",
            "37.8200",
            "37.6000",
            "34.7250",
            "40.4200",
            "42.5600",
            "34.5600",
            "43.3900",
            "40.3750",
            "41.9050",
            "41.0100",
            "38.6250",
            "39.7800",
            "34.5600",
            "39.4600",
            "40.9000"
          ],
          "total_count": 0,
          "probability": 1,
          "unique": 95,
          "has_duplicates": true
        }
      ],
      "total_count": 100,
      "type": "String",
      "has_duplicates": true,
      "probability": 1
    },
    {
      "name": "3-low",
      "path": "3-low",
      "count": 100,
      "types": [
        {
          "name": "String",
          "bsonType": "String",
          "path": "3-low",
          "count": 100,
          "values": [
            "42.0300",
            "42.0500",
            "40.4200",
            "42.1600",
            "36.6300",
            "34.0201",
            "42.1150",
            "38.2200",
            "38.4900",
            "36.8500",
            "38.0750",
            "42.1100",
            "41.6600",
            "37.5300",
            "40.4600",
            "37.4100",
            "34.6800",
            "39.2000",
            "42.6800",
            "42.2500",
            "35.1400",
            "41.6150",
            "35.5000",
            "42.4250",
            "39.8800",
            "40.9000",
            "41.3400",
            "35.9200",
            "41.4600",
            "35.2400",
            "40.7500",
            "42.6000",
            "39.0350",
            "32.5500",
            "37.5800",
            "39.5100",
            "39.5900",
            "32.8600",
            "36.9700",
            "39.4550",
            "41.1100",
            "38.9100",
            "39.2850",
            "41.5100",
            "41.3100",
            "37.4000",
            "40.8400",
            "41.8900",
            "36.8900",
            "32.9100",
            "42.8300",
            "38.0503",
            "39.6000",
            "38.4600",
            "41.1000",
            "41.2050",
            "39.5100",
            "42.7650",
            "35.7600",
            "35.6000",
            "41.2400",
            "40.7600",
            "39.2200",
            "42.1400",
            "37.2200",
            "37.8900",
            "36.8200",
            "35.8400",
            "40.7800",
            "38.1650",
            "40.7200",
            "34.4100",
            "37.3300",
            "41.9200",
            "38.7200",
            "38.9200",
            "39.7800",
            "35.8100",
            "40.6700",
            "38.4250",
            "39.7200",
            "41.1000",
            "36.3700",
            "41.9300",
            "39.2800",
            "36.7811",
            "36.1700",
            "34.1800",
            "40.0700",
            "41.0400",
            "33.7020",
            "43.0600",
            "39.8500",
            "41.0600",
            "40.1800",
            "37.8600",
            "39.0300",
            "33.7900",
            "38.6300",
            "40.4700"
          ],
          "total_count": 0,
          "probability": 1,
          "unique": 98,
          "has_duplicates": true
        }
      ],
      "total_count": 100,
      "type": "String",
      "has_duplicates": true,
      "probability": 1
    },
    {
      "name": "4-close",
      "path": "4-close",
      "count": 100,
      "types": [
        {
          "name": "String",
          "bsonType": "String",
          "path": "4-close",
          "count": 100,
          "values": [
            "42.0500",
            "42.3900",
            "40.5600",
            "42.7400",
            "37.6600",
            "34.1900",
            "42.5500",
            "39.1800",
            "38.7800",
            "37.2400",
            "38.6800",
            "42.3200",
            "42.0400",
            "38.5300",
            "41.1100",
            "38.7200",
            "34.7100",
            "39.3200",
            "43.2500",
            "42.6300",
            "35.5200",
            "41.6900",
            "35.5300",
            "42.8800",
            "40.0300",
            "41.3900",
            "41.5700",
            "36.5000",
            "41.8700",
            "35.7900",
            "40.8900",
            "42.9400",
            "39.1700",
            "32.8800",
            "37.9400",
            "39.9900",
            "40.0500",
            "32.9800",
            "37.6400",
            "39.6900",
            "42.1800",
            "39.1500",
            "39.4100",
            "41.8600",
            "41.9700",
            "37.6600",
            "41.6200",
            "42.4000",
            "36.9000",
            "33.3700",
            "43.2700",
            "38.7400",
            "39.8000",
            "38.6900",
            "41.5600",
            "41.5400",
            "39.8800",
            "42.9200",
            "35.9300",
            "36.3800",
            "42.0100",
            "41.3900",
            "39.7000",
            "42.1600",
            "37.7500",
            "38.0800",
            "37.1300",
            "36.4200",
            "41.8400",
            "38.3600",
            "41.2300",
            "35.1500",
            "37.9500",
            "42.3600",
            "39.4900",
            "39.8800",
            "41.0000",
            "36.3200",
            "41.6200",
            "38.9400",
            "39.8000",
            "41.1500",
            "37.3700",
            "42.0100",
            "39.9700",
            "36.9000",
            "36.9300",
            "34.5400",
            "40.2000",
            "41.1800",
            "34.2700",
            "43.1200",
            "40.0600",
            "41.3600",
            "40.8300",
            "38.3100",
            "39.7500",
            "34.4100",
            "38.9900",
            "40.5300"
          ],
          "total_count": 0,
          "probability": 1,
          "unique": 93,
          "has_duplicates": true
        }
      ],
      "total_count": 100,
      "type": "String",
      "has_duplicates": true,
      "probability": 1
    },
    {
      "name": "5-volume",
      "path": "5-volume",
      "count": 100,
      "types": [
        {
          "name": "String",
          "bsonType": "String",
          "path": "5-volume",
          "count": 100,
          "values": [
            "41271509",
            "38509710",
            "41940536",
            "32656416",
            "47517929",
            "37541679",
            "52981095",
            "48688095",
            "102774160",
            "45833982",
            "66846032",
            "42366332",
            "41332752",
            "106252691",
            "44008650",
            "37851803",
            "70677863",
            "46770430",
            "46981200",
            "31390752",
            "67440696",
            "40123631",
            "41167417",
            "41871447",
            "34084387",
            "39247942",
            "42964650",
            "96512823",
            "36871075",
            "45901659",
            "38519613",
            "34180477",
            "42321105",
            "29479877",
            "46069550",
            "45872878",
            "43136432",
            "44818705",
            "50300421",
            "42590122",
            "39249229",
            "60633444",
            "34699774",
            "31203614",
            "42672763",
            "54701323",
            "53178846",
            "40243780",
            "43896774",
            "37468264",
            "37192604",
            "118128903",
            "50328508",
            "49269961",
            "34416478",
            "28045093",
            "34304845",
            "42890652",
            "74507409",
            "58139468",
            "39044361",
            "37471100",
            "45285921",
            "37880308",
            "50194917",
            "50834128",
            "65335453",
            "66046957",
            "42026130",
            "48093367",
            "29159782",
            "56588551",
            "63795959",
            "30932586",
            "65586958",
            "52023788",
            "53879993",
            "63946003",
            "63559189",
            "95439685",
            "80728191",
            "28993974",
            "53365578",
            "52657668",
            "44113247",
            "49838043",
            "74292325",
            "54514131",
            "32039930",
            "47532956",
            "52802553",
            "28401875",
            "45544583",
            "36050674",
            "37161804",
            "45680016",
            "48119374",
            "45382971",
            "56705930",
            "39203386"
          ],
          "total_count": 0,
          "probability": 1,
          "unique": 100,
          "has_duplicates": false
        }
      ],
      "total_count": 100,
      "type": "String",
      "has_duplicates": false,
      "probability": 1
    },
    {
      "name": "index",
      "path": "index",
      "count": 100,
      "types": [
        {
          "name": "String",
          "bsonType": "String",
          "path": "index",
          "count": 100,
          "values": [
            "2021-05-10",
            "2021-05-28",
            "2021-05-03",
            "2021-05-17",
            "2021-03-25",
            "2021-02-18",
            "2021-05-27",
            "2021-04-23",
            "2021-06-18",
            "2021-03-11",
            "2021-03-26",
            "2021-06-09",
            "2021-05-26",
            "2021-03-19",
            "2021-04-29",
            "2021-04-21",
            "2021-02-26",
            "2021-04-13",
            "2021-06-03",
            "2021-05-24",
            "2021-02-23",
            "2021-06-10",
            "2021-03-02",
            "2021-06-08",
            "2021-04-28",
            "2021-06-15",
            "2021-05-11",
            "2021-03-04",
            "2021-05-20",
            "2021-03-01",
            "2021-06-29",
            "2021-06-02",
            "2021-04-19",
            "2021-02-11",
            "2021-03-12",
            "2021-04-09",
            "2021-04-07",
            "2021-02-10",
            "2021-03-16",
            "2021-04-06",
            "2021-05-07",
            "2021-04-16",
            "2021-04-26",
            "2021-06-11",
            "2021-05-19",
            "2021-03-22",
            "2021-06-25",
            "2021-05-21",
            "2021-03-24",
            "2021-02-12",
            "2021-06-04",
            "2021-04-15",
            "2021-04-05",
            "2021-03-31",
            "2021-06-28",
            "2021-07-01",
            "2021-04-27",
            "2021-06-01",
            "2021-02-25",
            "2021-02-24",
            "2021-05-06",
            "2021-05-05",
            "2021-04-08",
            "2021-05-18",
            "2021-03-15",
            "2021-04-20",
            "2021-03-08",
            "2021-03-03",
            "2021-05-13",
            "2021-04-22",
            "2021-06-30",
            "2021-02-22",
            "2021-03-17",
            "2021-05-14",
            "2021-04-01",
            "2021-04-14",
            "2021-05-04",
            "2021-03-09",
            "2021-06-16",
            "2021-03-18",
            "2021-06-17",
            "2021-07-02",
            "2021-03-10",
            "2021-05-25",
            "2021-06-22",
            "2021-03-23",
            "2021-03-05",
            "2021-02-19",
            "2021-06-23",
            "2021-05-12",
            "2021-02-16",
            "2021-06-07",
            "2021-04-12",
            "2021-06-14",
            "2021-06-24",
            "2021-03-29",
            "2021-06-21",
            "2021-02-17",
            "2021-03-30",
            "2021-04-30"
          ],
          "total_count": 0,
          "probability": 1,
          "unique": 100,
          "has_duplicates": false
        }
      ],
      "total_count": 100,
      "type": "String",
      "has_duplicates": false,
      "probability": 1
    }
  ],
  "count": 100
}