{
  "fields": [
    {
      "name": "_id",
      "path": "_id",
      "count": 100,
      "types": [
        {
          "name": "ObjectID",
          "bsonType": "ObjectID",
          "path": "_id",
          "count": 100,
          "values": [
            "60e32d7ca7329589de0b0b50",
            "60e32d7ca7329589de0b0b14",
            "60e32d7ca7329589de0b0b2b",
            "60e32d7ca7329589de0b0b20",
            "60e32d7ca7329589de0b0af8",
            "60e32d7ca7329589de0b0b54",
            "60e32d7ca7329589de0b0b30",
            "60e32d7ca7329589de0b0b07",
            "60e32d7ca7329589de0b0b45",
            "60e32d7ca7329589de0b0b17",
            "60e32d7ca7329589de0b0b15",
            "60e32d7ca7329589de0b0afd",
            "60e32d7ca7329589de0b0b26",
            "60e32d7ca7329589de0b0b1e",
            "60e32d7ca7329589de0b0b19",
            "60e32d7ca7329589de0b0afc",
            "60e32d7ca7329589de0b0b3c",
            "60e32d7ca7329589de0b0b10",
            "60e32d7ca7329589de0b0b47",
            "60e32d7ca7329589de0b0afb",
            "60e32d7ca7329589de0b0b5b",
            "60e32d7ca7329589de0b0b1a",
            "60e32d7ca7329589de0b0b49",
            "60e32d7ca7329589de0b0b33",
            "60e32d7ca7329589de0b0b31",
            "60e32d7ca7329589de0b0b43",
            "60e32d7ca7329589de0b0b44",
            "60e32d7ca7329589de0b0b0b",
            "60e32d7ca7329589de0b0b16",
            "60e32d7ca7329589de0b0b58",
            "60e32d7ca7329589de0b0b1c",
            "60e32d7ca7329589de0b0b27",
            "60e32d7ca7329589de0b0b4b",
            "60e32d7ca7329589de0b0afa",
            "60e32d7ca7329589de0b0b08",
            "60e32d7ca7329589de0b0b34",
            "60e32d7ca7329589de0b0aff",
            "60e32d7ca7329589de0b0b0c",
            "60e32d7ca7329589de0b0afe",
            "60e32d7ca7329589de0b0b0d",
            "60e32d7ca7329589de0b0b1b",
            "60e32d7ca7329589de0b0b39",
            "60e32d7ca7329589de0b0b2d",
            "60e32d7ca7329589de0b0b3a",
            "60e32d7ca7329589de0b0b0e",
            "60e32d7ca7329589de0b0b1d",
            "60e32d7ca7329589de0b0b41",
            "60e32d7ca7329589de0b0b56",
            "60e32d7ca7329589de0b0b0a",
            "60e32d7ca7329589de0b0b4a",
            "60e32d7ca7329589de0b0b32",
            "60e32d7ca7329589de0b0b13",
            "60e32d7ca7329589de0b0b53",
            "60e32d7ca7329589de0b0b36",
            "60e32d7ca7329589de0b0b48",
            "60e32d7ca7329589de0b0b2a",
            "60e32d7ca7329589de0b0b0f",
            "60e32d7ca7329589de0b0b3d",
            "60e32d7ca7329589de0b0b59",
            "60e32d7ca7329589de0b0b1f",
            "60e32d7ca7329589de0b0b38",
            "60e32d7ca7329589de0b0b42",
            "60e32d7ca7329589de0b0b06",
            "60e32d7ca7329589de0b0b02",
            "60e32d7ca7329589de0b0b3e",
            "60e32d7ca7329589de0b0b12",
            "60e32d7ca7329589de0b0b2f",
            "60e32d7ca7329589de0b0b05",
            "60e32d7ca7329589de0b0b37",
            "60e32d7ca7329589de0b0b01",
            "60e32d7ca7329589de0b0b5a",
            "60e32d7ca7329589de0b0b46",
            "60e32d7ca7329589de0b0af9",
            "60e32d7ca7329589de0b0b00",
            "60e32d7ca7329589de0b0b52",
            "60e32d7ca7329589de0b0b23",
            "60e32d7ca7329589de0b0b51",
            "60e32d7ca7329589de0b0b3b",
            "60e32d7ca7329589de0b0b3f",
            "60e32d7ca7329589de0b0b57",
            "60e32d7ca7329589de0b0b22",
            "60e32d7ca7329589de0b0b18",
            "60e32d7ca7329589de0b0b4e",
            "60e32d7ca7329589de0b0b2e",
            "60e32d7ca7329589de0b0b40",
            "60e32d7ca7329589de0b0b2c",
            "60e32d7ca7329589de0b0b04",
            "60e32d7ca7329589de0b0b29",
            "60e32d7ca7329589de0b0b24",
            "60e32d7ca7329589de0b0b35",
            "60e32d7ca7329589de0b0b28",
            "60e32d7ca7329589de0b0b03",
            "60e32d7ca7329589de0b0b09",
            "60e32d7ca7329589de0b0b4c",
            "60e32d7ca7329589de0b0b55",
            "60e32d7ca7329589de0b0b4f",
            "60e32d7ca7329589de0b0b25",
            "60e32d7ca7329589de0b0b4d",
            "60e32d7ca7329589de0b0b11",
            "60e32d7ca7329589de0b0b21"
          ],
          "total_count": 0,
          "probability": 1,
          "unique": 100,
          "has_duplicates": false
        }
      ],
      "total_count": 100,
      "type": "ObjectID",
      "has_duplicates": false,
      "probability": 1
    },
    {
      "name": "1-open",
      "path": "1-open",
      "count": 100,
      "types": [
        {
          "name": "String",
          "bsonType": "String",
          "path": "1-open",
          "count": 100,
          "values": [
            "66.7800",
            "77.8300",
            "69.1300",
            "73.6400",
            "71.0100",
            "65.4000",
            "71.7400",
            "77.0000",
            "75.5100",
            "75.6200",
            "76.5000",
            "71.4500",
            "73.3700",
            "75.3550",
            "76.3300",
            "71.3200",
            "72.5700",
            "78.6600",
            "73.4800",
            "70.1400",
            "63.4800",
            "75.6800",
            "70.9100",
            "72.8100",
            "72.3000",
            "73.9300",
            "73.5200",
            "79.6200",
            "76.1700",
            "64.9200",
            "75.9400",
            "72.5000",
            "70.8400",
            "69.6800",
            "79.0400",
            "72.1500",
            "69.3550",
            "79.6900",
            "70.3300",
            "79.7100",
            "73.8800",
            "72.7100",
            "72.7100",
            "72.0000",
            "80.1000",
            "74.5000",
            "73.2000",
            "64.3000",
            "78.3000",
            "71.0700",
            "72.6200",
            "78.2000",
            "65.5900",
            "72.3650",
            "71.2850",
            "70.4300",
            "79.4900",
            "69.8300",
            "62.9200",
            "73.4300",
            "72.2200",
            "74.4300",
            "76.6100",
            "68.4800",
            "71.6900",
            "77.2100",
            "74.4500",
            "75.0500",
            "74.0700",
            "68.4400",
            "63.6000",
            "74.4203",
            "71.0800",
            "68.9000",
            "67.1700",
            "72.0200",
            "69.0400",
            "71.5500",
            "71.3000",
            "63.8000",
            "71.2400",
            "77.3800",
            "69.1900",
            "73.3200",
            "72.2900",
            "71.5500",
            "72.7500",
            "69.8400",
            "72.6900",
            "72.9200",
            "71.7300",
            "72.5800",
            "78.6700",
            "70.1800",
            "64.1600",
            "68.4900",
            "73.7600",
            "69.4900",
            "78.5200",
            "72.6100"
          ],
          "total_count": 0,
          "probability": 1,
          "unique": 98,
          "has_duplicates": true
        }
      ],
      "total_count": 100,
      "type": "String",
      "has_duplicates": true,
      "probability": 1
    },
    {
      "name": "2-high",
      "path": "2-high",
      "count": 100,
      "types": [
        {
          "name": "String",
          "bsonType": "String",
          "path": "2-high",
          "count": 100,
          "values": [
            "67.5950",
            "78.3550",
            "70.7050",
            "74.9400",
            "71.1200",
            "66.8950",
            "73.2900",
            "77.1900",
            "75.5900",
            "76.6474",
            "77.8050",
            "71.8500",
            "73.6400",
            "76.8390",
            "77.4700",
            "71.6700",
            "73.2400",
            "78.9700",
            "74.2750",
            "71.6000",
            "63.9899",
            "76.7700",
            "72.4850",
            "73.0100",
            "72.4200",
            "74.3400",
            "73.6250",
            "79.6500",
            "76.6400",
            "65.0700",
            "76.4000",
            "73.1000",
            "71.2700",
            "70.8100",
            "79.2900",
            "72.5250",
            "70.0500",
            "79.8700",
            "71.6700",
            "80.2850",
            "75.8800",
            "73.8300",
            "72.8350",
            "73.2200",
            "80.2900",
            "75.5700",
            "73.5802",
            "64.5500",
            "79.4200",
            "72.8400",
            "72.8000",
            "79.2800",
            "66.9150",
            "73.0650",
            "73.8800",
            "70.7500",
            "80.0900",
            "71.9200",
            "64.0200",
            "75.1050",
            "73.2900",
            "76.1300",
            "76.7700",
            "68.7500",
            "72.4800",
            "77.9031",
            "74.7300",
            "75.3400",
            "74.3400",
            "69.0900",
            "63.8700",
            "75.2500",
            "71.2100",
            "69.4100",
            "68.6800",
            "72.4450",
            "69.3800",
            "72.1500",
            "72.6400",
            "64.9050",
            "72.4000",
            "77.6900",
            "69.9900",
            "73.5700",
            "72.6000",
            "71.5500",
            "73.0000",
            "71.5400",
            "72.7400",
            "73.1200",
            "72.8100",
            "72.6100",
            "78.7800",
            "71.7800",
            "65.9900",
            "69.9850",
            "74.0200",
            "71.4900",
            "79.1100",
            "73.8100"
          ],
          "total_count": 0,
          "probability": 1,
          "unique": 96,
          "has_duplicates": true
        }
      ],
      "total_count": 100,
      "type": "String",
      "has_duplicates": true,
      "probability": 1
    },
    {
      "name": "3-low",
      "path": "3-low",
      "count": 100,
      "types": [
        {
          "name": "String",
          "bsonType": "String",
          "path": "3-low",
          "count": 100,
          "values": [
            "65.5400",
            "77.4700",
            "68.4050",
            "73.4200",
            "70.1100",
            "65.2900",
            "71.3793",
            "76.1000",
            "73.2750",
            "74.7250",
            "76.4100",
            "69.8600",
            "72.7300",
            "75.1100",
            "76.1000",
            "70.4600",
            "72.0000",
            "77.9100",
            "72.5500",
            "69.5750",
            "62.9800",
            "75.6600",
            "70.0400",
            "72.0100",
            "71.0650",
            "72.7400",
            "72.3150",
            "79.0150",
            "75.3600",
            "63.8350",
            "73.9000",
            "72.3600",
            "68.4401",
            "69.4212",
            "76.8300",
            "71.0850",
            "69.0750",
            "78.8100",
            "69.9500",
            "79.4220",
            "73.8000",
            "72.4600",
            "71.9500",
            "72.0000",
            "79.3783",
            "73.9100",
            "71.5220",
            "63.0900",
            "77.7100",
            "70.8600",
            "72.1400",
            "77.1900",
            "64.8600",
            "72.0500",
            "71.2000",
            "69.6700",
            "79.3400",
            "69.1500",
            "62.8900",
            "73.2200",
            "72.2200",
            "73.4500",
            "74.6700",
            "67.1300",
            "70.0600",
            "76.6800",
            "71.7600",
            "73.2500",
            "72.4400",
            "67.8800",
            "61.9250",
            "74.1000",
            "70.4500",
            "67.7700",
            "67.0000",
            "71.3900",
            "66.8900",
            "70.3700",
            "70.5050",
            "63.4500",
            "70.6300",
            "76.5700",
            "68.8500",
            "71.6900",
            "71.6400",
            "69.2700",
            "70.1500",
            "69.5100",
            "71.0900",
            "71.9500",
            "71.6100",
            "68.1550",
            "77.7600",
            "67.8900",
            "64.0500",
            "67.9800",
            "72.8807",
            "69.3000",
            "77.9500",
            "71.7800"
          ],
          "total_count": 0,
          "probability": 1,
          "unique": 97,
          "has_duplicates": true
        }
      ],
      "total_count": 100,
      "type": "String",
      "has_duplicates": true,
      "probability": 1
    },
    {
      "name": "4-close",
      "path": "4-close",
      "count": 100,
      "types": [
        {
          "name": "String",
          "bsonType": "String",
          "path": "4-close",
          "count": 100,
          "values": [
            "65.8800",
            "78.0300",
            "70.6500",
            "74.7800",
            "70.4100",
            "65.5200",
            "72.9100",
            "76.4800",
            "74.2200",
            "76.4600",
            "77.6500",
            "71.5500",
            "72.9100",
            "75.1300",
            "77.4200",
            "71.5100",
            "73.0200",
            "78.7100",
            "73.3100",
            "69.6800",
            "63.6200",
            "76.5600",
            "70.9900",
            "72.4200",
            "72.0600",
            "73.6000",
            "73.3300",
            "79.3100",
            "76.2000",
            "64.1200",
            "74.2300",
            "72.9900",
            "70.2300",
            "70.7500",
            "76.8900",
            "72.3300",
            "69.6500",
            "79.4900",
            "71.3200",
            "79.6300",
            "75.2900",
            "72.7500",
            "72.1300",
            "72.9600",
            "79.8600",
            "74.8700",
            "73.0100",
            "63.4800",
            "79.0800",
            "72.2200",
            "72.6900",
            "77.2800",
            "66.7400",
            "72.6000",
            "73.7500",
            "69.8100",
            "79.7600",
            "71.7200",
            "63.6300",
            "75.0800",
            "73.1400",
            "73.8400",
            "75.1600",
            "67.6100",
            "70.0800",
            "77.5200",
            "72.5400",
            "73.8200",
            "72.7500",
            "68.4500",
            "63.2000",
            "75.1800",
            "71.0100",
            "68.9600",
            "68.6000",
            "71.7100",
            "67.4100",
            "71.5800",
            "70.9100",
            "64.7600",
            "72.3300",
            "76.6200",
            "68.9100",
            "72.4500",
            "71.9600",
            "69.7900",
            "71.4600",
            "71.3800",
            "71.2400",
            "72.6900",
            "72.2000",
            "68.8600",
            "78.1400",
            "69.8100",
            "65.7800",
            "69.5400",
            "73.8400",
            "70.3800",
            "78.7600",
            "73.7100"
          ],
          "total_count": 0,
          "probability": 1,
          "unique": 94,
          "has_duplicates": true
        }
      ],
      "total_count": 100,
      "type": "String",
      "has_duplicates": true,
      "probability": 1
    },
    {
      "name": "5-volume",
      "path": "5-volume",
      "count": 100,
      "types": [
        {
          "name": "String",
          "bsonType": "String",
          "path": "5-volume",
          "count": 100,
          "values": [
            "23788233",
            "16711847",
            "16334811",
            "19621804",
            "13227347",
            "23011138",
            "19476580",
            "18043544",
            "18936368",
            "23283609",
            "18544495",
            "26727435",
            "14420387",
            "19628200",
            "14676315",
            "17660887",
            "15716614",
            "14394377",
            "17499158",
            "28696913",
            "12368944",
            "14122726",
            "24194875",
            "14586378",
            "16150047",
            "19337521",
            "15834756",
            "12670074",
            "15244291",
            "19065436",
            "19791292",
            "13357476",
            "25406770",
            "18502309",
            "15277433",
            "13677091",
            "19672705",
            "13806958",
            "23900402",
            "22255785",
            "18630298",
            "15224796",
            "19964807",
            "15615908",
            "15285588",
            "21534800",
            "24079436",
            "14833206",
            "15399063",
            "27351130",
            "12002367",
            "20015794",
            "26712054",
            "12908401",
            "21331095",
            "16037648",
            "15450506",
            "18357283",
            "12174560",
            "16937385",
            "15251272",
            "23857885",
            "18304435",
            "44582888",
            "17089617",
            "15243442",
            "31333368",
            "25191652",
            "16128423",
            "30266626",
            "12108275",
            "17210559",
            "12584798",
            "21564644",
            "20752879",
            "16026109",
            "25098451",
            "17822340",
            "16238699",
            "20239597",
            "23071429",
            "13729630",
            "19200581",
            "28478391",
            "15039981",
            "22012998",
            "52981793",
            "18878095",
            "23669327",
            "14081388",
            "13098596",
            "48523025",
            "13778440",
            "28518413",
            "20456223",
            "28054645",
            "20628360",
            "25157635",
            "17466971",
            "19427200"
          ],
          "total_count": 0,
          "probability": 1,
          "unique": 100,
          "has_duplicates": false
        }
      ],
      "total_count": 100,
      "type": "String",
      "has_duplicates": false,
      "probability": 1
    },
    {
      "name": "index",
      "path": "index",
      "count": 100,
      "types": [
        {
          "name": "String",
          "bsonType": "String",
          "path": "index",
          "count": 100,
          "values": [
            "2021-02-26",
            "2021-05-24",
            "2021-04-21",
            "2021-05-06",
            "2021-07-02",
            "2021-02-22",
            "2021-04-14",
            "2021-06-11",
            "2021-03-15",
            "2021-05-19",
            "2021-05-21",
            "2021-06-25",
            "2021-04-28",
            "2021-05-10",
            "2021-05-17",
            "2021-06-28",
            "2021-03-26",
            "2021-05-28",
            "2021-03-11",
            "2021-06-29",
            "2021-02-10",
            "2021-05-14",
            "2021-03-09",
            "2021-04-09",
            "2021-04-13",
            "2021-03-17",
            "2021-03-16",
            "2021-06-07",
            "2021-05-20",
            "2021-02-16",
            "2021-05-12",
            "2021-04-27",
            "2021-03-05",
            "2021-06-30",
            "2021-06-10",
            "2021-04-08",
            "2021-06-23",
            "2021-06-04",
            "2021-06-24",
            "2021-06-03",
            "2021-05-13",
            "2021-03-31",
            "2021-04-19",
            "2021-03-30",
            "2021-06-02",
            "2021-05-11",
            "2021-03-19",
            "2021-02-18",
            "2021-06-08",
            "2021-03-08",
            "2021-04-12",
            "2021-05-25",
            "2021-02-23",
            "2021-04-06",
            "2021-03-10",
            "2021-04-22",
            "2021-06-01",
            "2021-03-25",
            "2021-02-12",
            "2021-05-07",
            "2021-04-01",
            "2021-03-18",
            "2021-06-14",
            "2021-06-18",
            "2021-03-24",
            "2021-05-26",
            "2021-04-15",
            "2021-06-15",
            "2021-04-05",
            "2021-06-21",
            "2021-02-11",
            "2021-03-12",
            "2021-07-01",
            "2021-06-22",
            "2021-02-24",
            "2021-05-03",
            "2021-02-25",
            "2021-03-29",
            "2021-03-23",
            "2021-02-17",
            "2021-05-04",
            "2021-05-18",
            "2021-03-02",
            "2021-04-16",
            "2021-03-22",
            "2021-04-20",
            "2021-06-16",
            "2021-04-23",
            "2021-04-30",
            "2021-04-07",
            "2021-04-26",
            "2021-06-17",
            "2021-06-09",
            "2021-03-04",
            "2021-02-19",
            "2021-03-01",
            "2021-04-29",
            "2021-03-03",
            "2021-05-27",
            "2021-05-05"
          ],
          "total_count": 0,
          "probability": 1,
          "unique": 100,
          "has_duplicates": false
        }
      ],
      "total_count": 100,
      "type": "String",
      "has_duplicates": false,
      "probability": 1
    }
  ],
  "count": 100
}